Metadata-Version: 1.1
Name: emojaddress
Version: 0.1.4
Summary: emoji mnemonic for Ethereum and Bitcoin addresses
Home-page: https://github.com/lonex/emojaddress
Author: stonelonely
Author-email: lonex@gmail.com
License: MIT license
Keywords: emojaddress
Platform: UNKNOWN
Classifier: Development Status :: 2 - Pre-Alpha
Classifier: Intended Audience :: Developers
Classifier: License :: OSI Approved :: MIT License
Classifier: Natural Language :: English
Classifier: Programming Language :: Python :: 3
Classifier: Programming Language :: Python :: 3.3
Classifier: Programming Language :: Python :: 3.4
Classifier: Programming Language :: Python :: 3.5
